gliderpy/__init__.py
gliderpy/_version.py
gliderpy/fetchers.py
gliderpy/plotting.py
gliderpy/servers.py
gliderpy-1.0.0.dist-info/licenses/LICENSE.txt
gliderpy-1.0.0.dist-info/METADATA
gliderpy-1.0.0.dist-info/WHEEL
gliderpy-1.0.0.dist-info/top_level.txt
gliderpy-1.0.0.dist-info/RECORD
