Metadata-Version: 2.4
Name: gliderpy
Version: 1.0.0
Summary: Glider Data Fetcher
Maintainer: Lindsay Abrams, Filipe Fernandes
Maintainer-email: Callum Rollo <c.rollo@outlook.com>
License: Copyright 2017 Filipe Fernandes and contributors
Project-URL: documentation, https://ioos.github.io/gliderpy
Project-URL: homepage, https://github.com/ioos/gliderpy
Project-URL: repository, https://github.com/ioos/gliderpy
Classifier: Programming Language :: Python :: 3 :: Only
Classifier: Programming Language :: Python :: 3.10
Classifier: Programming Language :: Python :: 3.11
Classifier: Programming Language :: Python :: 3.12
Classifier: Programming Language :: Python :: 3.13
Requires-Python: >=3.10
License-File: LICENSE.txt
Requires-Dist: erddapy
Requires-Dist: httpx
Requires-Dist: pandas
Requires-Dist: pandas-flavor
Requires-Dist: stamina
Requires-Dist: xarray
Provides-Extra: docs
Requires-Dist: jupyter; extra == "docs"
Requires-Dist: nbconvert; extra == "docs"
Requires-Dist: nbsphinx; extra == "docs"
Requires-Dist: palettable; extra == "docs"
Requires-Dist: sphinx; extra == "docs"
Provides-Extra: plotting
Requires-Dist: cartopy; extra == "plotting"
Requires-Dist: gsw; extra == "plotting"
Requires-Dist: matplotlib; extra == "plotting"
Provides-Extra: test
Requires-Dist: check-manifest; extra == "test"
Requires-Dist: pre-commit; extra == "test"
Requires-Dist: pytest; extra == "test"
Requires-Dist: pytest-cov; extra == "test"
Requires-Dist: pytest-mpl; extra == "test"
Requires-Dist: pytest-sugar; extra == "test"
Requires-Dist: pytest-vcr; extra == "test"
Requires-Dist: pytest-xdist; extra == "test"
Dynamic: license-file
